evaluateur/__init__.py
evaluateur/_internal/__init__.py
evaluateur/_internal/async_iter.py
evaluateur/_internal/evaluator_factories.py
evaluateur/_internal/evaluator_goal_guidance.py
evaluateur/client.py
evaluateur/configs/__init__.py
evaluateur/configs/query.py
evaluateur/configs/tuple.py
evaluateur/evaluator.py
evaluateur/generators/__init__.py
evaluateur/generators/options.py
evaluateur/generators/queries.py
evaluateur/generators/query/__init__.py
evaluateur/generators/query/context.py
evaluateur/generators/query/instructor.py
evaluateur/generators/query/mode.py
evaluateur/generators/query/prompts.py
evaluateur/generators/query/protocols.py
evaluateur/generators/tuple/__init__.py
evaluateur/generators/tuple/cross_product.py
evaluateur/generators/tuple/direct_llm.py
evaluateur/generators/tuple/options_adapter.py
evaluateur/generators/tuple/protocols.py
evaluateur/generators/tuple/strategy.py
evaluateur/generators/tuples.py
evaluateur/goals.py
evaluateur/models.py
evaluateur/py.typed
evaluateur/types.py
evaluateur-0.2.0.dist-info/WHEEL
evaluateur-0.2.0.dist-info/METADATA
evaluateur-0.2.0.dist-info/RECORD
