Metadata-Version: 2.3
Name: evaluateur
Version: 0.2.0
Summary: synthetic evals for agents
Author: Sasha Aptlin
Author-email: Sasha Aptlin <sasha@aptford.com>
License: MIT
Requires-Dist: instructor>=1.13.0
Requires-Dist: pydantic>=2.12.5
Requires-Dist: python-dotenv>=1.2.1
Requires-Python: >=3.10, <4.0
Project-URL: documentation, https://github.com/aptford/evaluateur/blob/main/README.md
Project-URL: homepage, https://github.com/aptford/evaluateur
Project-URL: repository, https://github.com/aptford/evaluateur
